Metadata-Version: 1.1
Name: husk
Version: 0.1.2
Summary: Husk is an API and CLI written in Python for the Cornell Note-taking System.
Home-page: https://bruth.github.com/husk/
Author: Byron Ruth, Patrick Henning
Author-email: b@devel.io
License: BSD
Keywords: note-taking Cornell
Platform: UNKNOWN
Classifier: Development Status :: 4 - Beta
Classifier: License :: OSI Approved :: BSD License
Classifier: Programming Language :: Python :: 2.7
